pypiquery.py
pypiquery-0.0.2.dist-info/LICENSE.txt
pypiquery-0.0.2.dist-info/METADATA
pypiquery-0.0.2.dist-info/WHEEL
pypiquery-0.0.2.dist-info/entry_points.txt
pypiquery-0.0.2.dist-info/top_level.txt
pypiquery-0.0.2.dist-info/RECORD
