Metadata-Version: 2.1
Name: pypiquery
Version: 0.0.2
Summary: 通过查询 pypi.org 网站获取指定软件包历史版本信息。
Author: do0ob
License: MIT
Classifier: Environment :: Console
Classifier: License :: OSI Approved :: MIT License
Classifier: Programming Language :: Python
Classifier: Programming Language :: Python :: 3
License-File: LICENSE.txt
Requires-Dist: keyboard
Requires-Dist: requests
Requires-Dist: beautifulsoup4
